link_categorizer/__init__.py
link_categorizer/categorizer.py
link_categorizer/py.typed
link_categorizer-0.1.9.dist-info/METADATA
link_categorizer-0.1.9.dist-info/WHEEL
link_categorizer-0.1.9.dist-info/RECORD
