Metadata-Version: 2.4
Name: link_categorizer
Version: 0.1.9
Summary: A Python library that categorizes HTML links based on their domain names, title text, and anchor text.
Project-URL: Homepage, https://github.com/heysamtexas/link-categorizer
Project-URL: Bug Tracker, https://github.com/heysamtexas/link-categorizer/issues
Author-email: Sam Texas <dev@simplecto.com>
License: MIT
Classifier: License :: OSI Approved :: MIT License
Classifier: Operating System :: OS Independent
Classifier: Programming Language :: Python :: 3
Requires-Python: >=3.8
Provides-Extra: dev
Requires-Dist: bandit[toml]<1.8.0,>=1.7.0; extra == 'dev'
Requires-Dist: mypy>=1.4.0; extra == 'dev'
Requires-Dist: pre-commit>=2.21.0; extra == 'dev'
Requires-Dist: pytest-cov>=4.0.0; extra == 'dev'
Requires-Dist: pytest>=7.0.0; extra == 'dev'
Requires-Dist: ruff>=0.11.0; extra == 'dev'
Requires-Dist: types-pyyaml>=6.0.0; extra == 'dev'
